{
  "animateLoading": true,
  "borderRadius": "{{appsmith.theme.borderRadius.appBorderRadius}}",
  "bottomRow": 42,
  "boxShadow": "none",
  "buttonColor": "{{appsmith.theme.colors.primaryColor}}",
  "buttonStyle": "PRIMARY",
  "buttonVariant": "SECONDARY",
  "disabledWhenInvalid": false,
  "dynamicBindingPathList": [
    {
      "key": "buttonColor"
    },
    {
      "key": "borderRadius"
    }
  ],
  "dynamicTriggerPathList": [
    {
      "key": "onClick"
    }
  ],
  "isDefaultClickDisabled": true,
  "isDisabled": false,
  "isLoading": false,
  "isVisible": true,
  "key": "r60t3tyzlb",
  "leftColumn": 47,
  "minWidth": 120,
  "mobileBottomRow": 22,
  "mobileLeftColumn": 31,
  "mobileRightColumn": 47,
  "mobileTopRow": 18,
  "needsErrorInfo": false,
  "onClick": "{{closeModal(Modal2.name);}}",
  "parentId": "s2r6oko5f4",
  "placement": "CENTER",
  "recaptchaType": "V3",
  "renderMode": "CANVAS",
  "resetFormOnClick": false,
  "responsiveBehavior": "hug",
  "rightColumn": 63,
  "text": "Close",
  "topRow": 38,
  "type": "BUTTON_WIDGET",
  "version": 1,
  "widgetId": "6kojxw3e1n",
  "widgetName": "Button3"
}